__init__.py
functions.py
main.py
22BEE0039-0.0.1.dist-info/LICENSE
22BEE0039-0.0.1.dist-info/METADATA
22BEE0039-0.0.1.dist-info/WHEEL
22BEE0039-0.0.1.dist-info/top_level.txt
22BEE0039-0.0.1.dist-info/RECORD
